Workbook

Sheet Datos
B3: Metodo de pago | D3: semana | F3: Dia | I3: Base de Datos (Clientes, Proveedores y Terceros | K3: Gastos
B4: Transferencia | D4: semana 3 | F4: 46157 | I4: Nicolle | K4: Impresión de etiquetas
B5: Efectivo | D5: semana 4 | F5: 46158 | I5: Alexandra | K5: Honorarios y Prestacion de Servicio
B6: Credito | D6: semana 5 | F6: 46159 | I6: Tomas | K6: Gastos por arriendos
B7: Tarjeta | D7: semana 6 | F7: 46160 | I7: Sthepany | K7: Gastos por seguros
D8: semana 7 | F8: 46161 | I8: Gerson | K8: Gastos por servicios
D9: semana 8 | F9: 46162 | I9: Keren | K9: Gastos Legales
D10: semana 9 | F10: 46163 | I10: Cliente Activación | K10: Gasto de Mantenimiento y Reparaciones
D11: semana 10 | F11: 46164 | I11: Cliente Feria | K11: Gastos de viajes
D12: semana 11 | F12: 46165 | I12: Cliente lanzamiento | K12: Otros Gastos
D13: semana 12 | F13: 46166 | I13: Ingris G. negocios | K13: Gastos Bancarios
F14: 46167 | I14: Evelyn Andino | K14: Gastos por interes
F15: 46168 | I15: Fanys Moreno | K15: Otros Gastos Financieros
F16: 46169 | I16: Emely G. negocios | K16: Impuesto de Renta
F17: 46170 | I17: Melissa Canaca | K17: Otros impuestos
F18: 46171 | I18: Fabiola Romero
F19: 46172 | I19: Dilcia UNAH
F20: 46173 | I20: Olman Alvares
F21: 46174 | I21: Sharon Raudales
F22: 46175 | I22: Lic Cesar | K22: Articulos Inventarios
F23: 46176 | I23: David Castillo | K23: Pica extremo
F24: 46177 | I24: Hever Perdomo | K24: Pica rico
F25: 46178 | I25: Francisco Abularach | K25: Pica suave
F26: 46179 | I26: Dionicio Indufesa
F27: 46180 | I27: Obed Sanchez
F28: 46181 | I28: Lamber Giron
F29: 46182 | I29: Bryan Cruz
F30: 46183 | I30: Roberto Ferrera
F31: 46184 | I31: Ramon Cabrera
F32: 46185 | I32: Nelson Cabrera
F33: 46186 | I33: Exon Sierra
F34: 46187 | I34: Consumidor Final
F35: 46188 | I35: Carlos Josiel Hernadez
F36: 46189 | I36: Melvin indufesa
F37: 46190 | I37: estefany meza
... F43: 46196 | I43: Franklin Paredes
F44: 46197
F45: 46198
F46: 46199
F47: 46200
F48: 46201
F49: 46202
F50: 46203
F51: 46204
F52: 46205
F53: 46206
F54: 46207
F55: 46208
... F81: 46234

Sheet Product
B3: Productos
B4: Item | C4: Nombre | D4: Precio V. Unitario
B5: 1 | C5: =Datos!K23 -> Pica extremo | D5: 130
B6: 2 | C6: =Datos!K24 -> Pica rico | D6: 130
B7: 3 | C7: =Datos!K25 -> Pica suave | D7: 130
B8: 4 | C8: Combo | D8: 180
B9: 5 | C9: pica extremo pequeño | D9: 70
B10: 6 | C10: pica rico pequeño | D10: 70
B11: 7 | C11: pica suave pequeño | D11: 70

Sheet Venta
B2: LIBRO DE VENTAS
B3: Semana | C3: Dia | D3: Cliente | E3: Vendedor | F3: Producto/Servicio | G3: Valor Unitario | H3: Cantidad | I3: Valor total | J3: Forma de Pago | K3: Observaciones | L3: Canal de venta
B4: semana 3 | C4: 46168 | D4: Cliente lanzamiento | F4: Pica extremo | G4: =SUMIFS(Product!$D$5:$D$24,Product!$C$5:$C$24,Venta!F4) -> 130 | H4: 6 | I4: =G4*H4 -> 780 | J4: efectivo
B5: semana 3 | C5: 46168 | D5: Cliente lanzamiento | F5: Pica extremo | G5: =SUMIFS(Product!$D$5:$D$24,Product!$C$5:$C$24,Venta!F5) -> 130 | H5: 9 | I5: =G5*H5 -> 1170 | J5: Transferencia
B6: semana 3 | C6: 46168 | D6: Cliente lanzamiento | F6: Pica rico | G6: =SUMIFS(Product!$D$5:$D$24,Product!$C$5:$C$24,Venta!F6) -> 130 | H6: 4 | I6: =G6*H6 -> 520 | J6: efectivo
B7: semana 3 | C7: 46168 | D7: Cliente lanzamiento | F7: Pica rico | G7: =SUMIFS(Product!$D$5:$D$24,Product!$C$5:$C$24,Venta!F7) -> 130 | H7: 6 | I7: =G7*H7 -> 780 | J7: Transferencia
B8: semana 3 | C8: 46168 | D8: Cliente lanzamiento | F8: Pica suave | G8: =SUMIFS(Product!$D$5:$D$24,Product!$C$5:$C$24,Venta!F8) -> 130 | H8: 1 | I8: =G8*H8 -> 130 | J8: efectivo | M8: TOTAL LANZAMIENTO
B9: semana 3 | C9: 46168 | D9: Cliente lanzamiento | F9: Pica suave | G9: =SUMIFS(Product!$D$5:$D$24,Product!$C$5:$C$24,Venta!F9) -> 130 | H9: 3 | I9: =G9*H9 -> 390 | J9: Transferencia | M9: =SUM(H4:H9) -> 29
B10: semana 3 | C10: 46169 | D10: dilcia unah | E10: keren | F10: Pica extremo | G10: =SUMIFS(Product!$D$5:$D$24,Product!$C$5:$C$24,Venta!F15) -> 130 | H10: 1 | I10: =G10*H10 -> 130 | J10: efectivo | L10: Directo
B11: semana 3 | C11: 46169 | E11: keren | F11: pica suave | G11: =SUMIFS(Product!$D$5:$D$24,Product!$C$5:$C$24,Venta!F20) -> 130 | H11: 1 | I11: =G11*H11 -> 130 | J11: efectivo | L11: Directo
B12: semana 3 | C12: 46169 | D12: Evelyn Andino | E12: Nicolle | F12: Pica extremo | G12: =SUMIFS(Product!$D$5:$D$24,Product!$C$5:$C$24,Venta!F12) -> 130 | H12: 1 | I12: =G12*H12 -> 130 | J12: Transferencia | L12: Directo
B13: semana 3 | C13: 46169 | D13: Nicolle | E13: Nicolle | F13: Pica extremo | G13: =SUMIFS(Product!$D$5:$D$24,Product!$C$5:$C$24,Venta!F14) -> 130 | H13: 1 | I13: =G13*H13 -> 130 | J13: Transferencia | L13: Directo
B14: semana 3 | C14: 46169 | D14: fabiola romero | E14: Nicolle | F14: Pica extremo | G14: =SUMIFS(Product!$D$5:$D$24,Product!$C$5:$C$24,Venta!F16) -> 130 | H14: 1 | I14: =G14*H14 -> 130 | J14: Transferencia | L14: Directo
B15: semana 3 | C15: 46169 | D15: lic cesar | E15: Nicolle | F15: Pica extremo | G15: =SUMIFS(Product!$D$5:$D$24,Product!$C$5:$C$24,Venta!F21) -> 130 | H15: 1 | I15: =G15*H15 -> 130 | J15: efectivo | L15: Directo
B16: semana 3 | C16: 46169 | D16: David Castillo | E16: Nicolle | F16: Pica extremo | G16: =SUMIFS(Product!$D$5:$D$24,Product!$C$5:$C$24,Venta!F22) -> 130 | H16: 2 | I16: =G16*H16 -> 260 | J16: efectivo | L16: Directo
B17: semana 3 | C17: 46169 | D17: sthepany | E17: sthepany | F17: Pica rico | G17: =SUMIFS(Product!$D$5:$D$24,Product!$C$5:$C$24,Venta!F18) -> 130 | H17: 1 | I17: =G17*H17 -> 130 | J17: efectivo | L17: Directo
B18: semana 3 | C18: 46169 | D18: Ingris G. negocios | E18: Nicolle | F18: Pica rico | G18: =SUMIFS(Product!$D$5:$D$24,Product!$C$5:$C$24,Venta!F10) -> 130 | H18: 1 | I18: =G18*H18 -> 130 | J18: efectivo | L18: Directo
B19: semana 3 | C19: 46169 | D19: Emely G. negocios | E19: Nicolle | F19: Pica rico | G19: =SUMIFS(Product!$D$5:$D$24,Product!$C$5:$C$24,Venta!F11) -> 130 | H19: 1 | I19: =G19*H19 -> 130 | J19: efectivo | L19: Directo
B20: semana 3 | C20: 46169 | D20: Fanys Moreno | E20: Nicolle | F20: Pica rico | G20: =SUMIFS(Product!$D$5:$D$24,Product!$C$5:$C$24,Venta!F13) -> 130 | H20: 1 | I20: =G20*H20 -> 130 | J20: Transferencia | L20: Directo
B21: semana 3 | C21: 46169 | D21: olman alvares | E21: Keren | F21: Pica suave | G21: =SUMIFS(Product!$D$5:$D$24,Product!$C$5:$C$24,Venta!F17) -> 130 | H21: 1 | I21: =G21*H21 -> 130 | J21: efectivo | L21: Directo
B22: semana 3 | C22: 46169 | D22: melissa canaca | E22: Nicolle | F22: Pica suave | G22: =SUMIFS(Product!$D$5:$D$24,Product!$C$5:$C$24,Venta!F19) -> 130 | H22: 1 | I22: =G22*H22 -> 130 | J22: Transferencia | L22: Directo
B23: semana 3 | C23: 46170 | D23: francisco abularach | E23: Nicolle | F23: Pica extremo | G23: =SUMIFS(Product!$D$5:$D$24,Product!$C$5:$C$24,Venta!F23) -> 130 | H23: 1 | I23: =G23*H23 -> 130 | J23: efectivo | L23: Directo
B24: semana 3 | C24: 46170 | D24: dionicio indufesa | E24: Nicolle | F24: Pica extremo | G24: =SUMIFS(Product!$D$5:$D$24,Product!$C$5:$C$24,Venta!F24) -> 130 | H24: 1 | I24: =G24*H24 -> 130 | J24: efectivo | L24: Directo
B25: semana 3 | C25: 46170 | D25: obed sanchez | E25: Nicolle | F25: Pica extremo | G25: =SUMIFS(Product!$D$5:$D$24,Product!$C$5:$C$24,Venta!F25) -> 130 | H25: 1 | I25: =G25*H25 -> 130 | J25: efectivo | L25: Directo
B26: semana 3 | C26: 46170 | D26: Lamber Giron | E26: Nicolle | F26: Pica extremo | G26: =SUMIFS(Product!$D$5:$D$24,Product!$C$5:$C$24,Venta!F26) -> 130 | H26: 1 | I26: =G26*H26 -> 130 | J26: Transferencia | L26: Directo
B27: semana 3 | C27: 46170 | D27: hever perdomo | E27: Nicolle | F27: Pica extremo | G27: =SUMIFS(Product!$D$5:$D$24,Product!$C$5:$C$24,Venta!F26) -> 130 | H27: 2 | I27: =G27*H27 -> 260 | J27: Transferencia | L27: Directo
B28: semana 3 | C28: 46170 | D28: Consumidor Final | E28: Alexandra | F28: Pica suave | G28: =SUMIFS(Product!$D$5:$D$24,Product!$C$5:$C$24,Venta!F29) -> 130 | H28: 5 | I28: =G28*H28 -> 650 | J28: efectivo | L28: Directo
B29: semana 3 | C29: 46170 | D29: Consumidor Final | E29: Alexandra | F29: Pica rico | G29: =SUMIFS(Product!$D$5:$D$24,Product!$C$5:$C$24,Venta!F30) -> 130 | H29: 6 | I29: =G29*H29 -> 780 | J29: Transferencia | L29: Directo
B30: semana 3 | C30: 46170 | D30: Consumidor Final | E30: Alexandra | F30: Pica extremo | G30: =SUMIFS(Product!$D$5:$D$24,Product!$C$5:$C$24,Venta!F31) -> 130 | H30: 6 | I30: =G30*H30 -> 780 | J30: Transferencia | L30: Directo
B31: semana 3 | C31: 46170 | D31: David Castillo | E31: Nicolle | F31: Pica rico | G31: =SUMIFS(Product!$D$5:$D$24,Product!$C$5:$C$24,Venta!F28) -> 130 | H31: 1 | I31: =G31*H31 -> 130 | J31: Transferencia | L31: Directo
B32: semana 3 | C32: 46170 | D32: bryan cruz | E32: Tomas | F32: Pica extremo | G32: =SUMIFS(Product!$D$5:$D$24,Product!$C$5:$C$24,Venta!F33) -> 130 | H32: 1 | I32: =G32*H32 -> 130 | J32: Transferencia | L32: Directo
B33: semana 3 | C33: 46170 | D33: David Castillo | E33: Nicolle | F33: Pica suave | G33: =SUMIFS(Product!$D$5:$D$24,Product!$C$5:$C$24,Venta!F27) -> 130 | H33: 2 | I33: =G33*H33 -> 260 | J33: Transferencia | L33: Directo
B34: semana 3 | C34: 46171 | D34: roberto ferrera | E34: Nicolle | F34: Pica extremo | G34: =SUMIFS(Product!$D$5:$D$24,Product!$C$5:$C$24,Venta!F34) -> 130 | H34: 1 | I34: =G34*H34 -> 130 | J34: Transferencia | L34: Directo
B35: semana 3 | C35: 46171 | D35: Consumidor Final | E35: Gerson | F35: Pica rico | G35: =SUMIFS(Product!$D$5:$D$24,Product!$C$5:$C$24,Venta!F37) -> 130 | H35: 1 | I35: =G35*H35 -> 130 | J35: Transferencia | L35: Directo
B36: semana 3 | C36: 46171 | D36: Ramon Cabrera | E36: Tomas | F36: Pica extremo | G36: =SUMIFS(Product!$D$5:$D$24,Product!$C$5:$C$24,Venta!F35) -> 130 | H36: 1 | I36: =G36*H36 -> 130 | J36: Transferencia | L36: Directo
B37: semana 3 | C37: 46171 | D37: Nelson Cabrera | E37: Tomas | F37: Pica extremo | G37: =SUMIFS(Product!$D$5:$D$24,Product!$C$5:$C$24,Venta!F36) -> 130 | H37: 1 | I37: =G37*H37 -> 130 | J37: Transferencia | L37: Directo
B38: semana 3 | C38: 46172 | D38: Sthepany | E38: Sthepany | F38: Pica extremo | G38: =SUMIFS(Product!$D$5:$D$24,Product!$C$5:$C$24,Venta!F38) -> 130 | H38: 5 | I38: =G38*H38 -> 650 | J38: Transferencia | L38: Directo
B39: semana 3 | C39: 46172 | D39: Exon Sierra | E39: Tomas | F39: pica suave | G39: =SUMIFS(Product!$D$5:$D$24,Product!$C$5:$C$24,Venta!F39) -> 130 | H39: 1 | I39: =G39*H39 -> 130 | J39: Transferencia | L39: Directo
B40: semana 4 | C40: 46175 | D40: Consumidor Final | E40: tomas | F40: Pica extremo | G40: =SUMIFS(Product!$D$5:$D$24,Product!$C$5:$C$24,Venta!F41) -> 130 | H40: 1 | I40: =G40*H40 -> 130 | J40: Transferencia | L40: Directo
B41: semana 4 | C41: 46176 | D41: Consumidor Final | E41: Tomas | F41: Pica extremo | G41: =SUMIFS(Product!$D$5:$D$24,Product!$C$5:$C$24,Venta!F65) -> 130 | H41: 1 | I41: =G41*H41 -> 130 | J41: efectivo | L41: Directo
B42: semana 4 | C42: 46175 | D42: Consumidor Final | E42: tomas | F42: Pica rico | G42: =SUMIFS(Product!$D$5:$D$24,Product!$C$5:$C$24,Venta!F44) -> 130 | H42: 1 | I42: =G42*H42 -> 130 | J42: efectivo | L42: Directo
B43: semana 4 | C43: 46175 | D43: Consumidor Final | E43: tomas | F43: pica rico | G43: =SUMIFS(Product!$D$5:$D$24,Product!$C$5:$C$24,Venta!F42) -> 130 | H43: 2 | I43: =G43*H43 -> 260 | J43: Transferencia | L43: Directo
B44: semana 4 | C44: 46175 | D44: Consumidor Final | E44: Nicolle | F44: Pica extremo | G44: =SUMIFS(Product!$D$5:$D$24,Product!$C$5:$C$24,Venta!F45) -> 130 | H44: 1 | I44: =G44*H44 -> 130 | J44: Transferencia | L44: Directo
B45: semana 4 | C45: 46175 | D45: Consumidor Final | E45: Tomas | F45: Pica rico | G45: =SUMIFS(Product!$D$5:$D$24,Product!$C$5:$C$24,Venta!F47) -> 130 | H45: 1 | I45: =G45*H45 -> 130 | J45: Transferencia | L45: Directo
B46: semana 4 | C46: 46175 | D46: Consumidor Final | E46: Tomas | F46: Pica rico | G46: =SUMIFS(Product!$D$5:$D$24,Product!$C$5:$C$24,Venta!F49) -> 130 | H46: 1 | I46: =G46*H46 -> 130 | J46: Transferencia | L46: Directo
B47: semana 4 | C47: 46176 | D47: Consumidor Final | E47: Tomas | F47: Pica rico | G47: =SUMIFS(Product!$D$5:$D$24,Product!$C$5:$C$24,Venta!F54) -> 130 | H47: 2 | I47: =G47*H47 -> 260 | J47: efectivo | L47: Directo
B48: semana 4 | C48: 46176 | D48: Consumidor Final | E48: Tomas | F48: Pica rico | G48: =SUMIFS(Product!$D$5:$D$24,Product!$C$5:$C$24,Venta!F53) -> 130 | H48: 1 | I48: =G48*H48 -> 130 | J48: Transferencia | L48: Directo
B49: semana 4 | C49: 46175 | D49: Consumidor Final | E49: tomas | F49: pica suave | G49: =SUMIFS(Product!$D$5:$D$24,Product!$C$5:$C$24,Venta!F43) -> 130 | H49: 1 | I49: =G49*H49 -> 130 | J49: efectivo | L49: Directo
B50: semana 4 | C50: 46175 | D50: Consumidor Final | E50: tomas | F50: Pica suave | G50: =SUMIFS(Product!$D$5:$D$24,Product!$C$5:$C$24,Venta!F50) -> 130 | H50: 1 | I50: =G50*H50 -> 130 | J50: Transferencia | L50: Directo
B51: semana 4 | C51: 46176 | D51: Consumidor Final | E51: Gerson | F51: Pica extremo | G51: =SUMIFS(Product!$D$5:$D$24,Product!$C$5:$C$24,Venta!F52) -> 130 | H51: 2 | I51: =G51*H51 -> 260 | J51: Transferencia | L51: Directo
B52: semana 4 | C52: 46176 | D52: Consumidor Final | E52: Gerson | F52: pica rico | G52: =SUMIFS(Product!$D$5:$D$24,Product!$C$5:$C$24,Venta!F51) -> 130 | H52: 2 | I52: =G52*H52 -> 260 | J52: Transferencia | L52: Directo
B53: semana 4 | C53: 46175 | D53: Consumidor Final | E53: Tomas | F53: Pica suave | G53: =SUMIFS(Product!$D$5:$D$24,Product!$C$5:$C$24,Venta!F46) -> 130 | H53: 1 | I53: =G53*H53 -> 130 | J53: Transferencia | L53: Directo
B54: semana 4 | C54: 46176 | D54: Consumidor Final | E54: Gerson | F54: Pica suave | G54: =SUMIFS(Product!$D$5:$D$24,Product!$C$5:$C$24,Venta!F50) -> 130 | H54: 1 | I54: =G54*H54 -> 130 | J54: Transferencia | L54: Directo
B55: semana 4 | C55: 46175 | D55: Consumidor Final | E55: Tomas | F55: pica suave | G55: =SUMIFS(Product!$D$5:$D$24,Product!$C$5:$C$24,Venta!F48) -> 130 | H55: 1 | I55: =G55*H55 -> 130 | J55: Transferencia | L55: Directo
B56: semana 4 | C56: 46176 | D56: Consumidor Final | E56: Tomas | F56: Pica suave | G56: =SUMIFS(Product!$D$5:$D$24,Product!$C$5:$C$24,Venta!F66) -> 130 | H56: 1 | I56: =G56*H56 -> 130 | J56: efectivo | L56: Directo
B57: semana 4 | C57: 46177 | D57: Consumidor Final | E57: sthepany | F57: Pica extremo | G57: =SUMIFS(Product!$D$5:$D$24,Product!$C$5:$C$24,Venta!F56) -> 130 | H57: 2 | I57: =G57*H57 -> 260 | J57: Transferencia | L57: Directo
B58: semana 4 | C58: 46177 | D58: Consumidor Final | E58: sthepany | F58: Pica extremo | G58: =SUMIFS(Product!$D$5:$D$24,Product!$C$5:$C$24,Venta!F62) -> 130 | H58: 1 | I58: =G58*H58 -> 130 | J58: Transferencia | L58: Directo
B59: semana 4 | C59: 46177 | D59: Consumidor Final | E59: sthepany | F59: Pica rico | G59: =SUMIFS(Product!$D$5:$D$24,Product!$C$5:$C$24,Venta!F57) -> 130 | H59: 2 | I59: =G59*H59 -> 260 | J59: Transferencia | L59: Directo
B60: semana 4 | C60: 46177 | D60: Consumidor Final | E60: keren | F60: Pica extremo | G60: =SUMIFS(Product!$D$5:$D$24,Product!$C$5:$C$24,Venta!F59) -> 130 | H60: 2 | I60: =G60*H60 -> 260 | J60: efectivo | L60: Directo
B61: semana 4 | C61: 46177 | D61: Consumidor Final | E61: keren | F61: Pica rico | G61: =SUMIFS(Product!$D$5:$D$24,Product!$C$5:$C$24,Venta!F60) -> 130 | H61: 3 | I61: =G61*H61 -> 390 | J61: efectivo | L61: Directo
B62: semana 4 | C62: 46177 | D62: Consumidor Final | E62: keren | F62: Pica suave | G62: =SUMIFS(Product!$D$5:$D$24,Product!$C$5:$C$24,Venta!F61) -> 130 | H62: 6 | I62: =G62*H62 -> 780 | J62: efectivo | L62: Directo
B63: semana 4 | C63: 46177 | D63: Consumidor Final | E63: sthepany | F63: pica suave | G63: =SUMIFS(Product!$D$5:$D$24,Product!$C$5:$C$24,Venta!F58) -> 130 | H63: 1 | I63: =G63*H63 -> 130 | J63: Transferencia | L63: Directo
B64: semana 4 | C64: 46177 | D64: Consumidor Final | E64: Tomas | F64: Pica suave | G64: =SUMIFS(Product!$D$5:$D$24,Product!$C$5:$C$24,Venta!F55) -> 130 | H64: 1 | I64: =G64*H64 -> 130 | J64: Transferencia | L64: Directo
B65: semana 4 | C65: 46180 | D65: Consumidor Final | E65: Gerson | F65: pica rico | G65: =SUMIFS(Product!$D$5:$D$24,Product!$C$5:$C$24,Venta!F64) -> 130 | H65: 1 | I65: =G65*H65 -> 130 | J65: Transferencia | L65: Directo
B66: semana 4 | C66: 46180 | D66: Consumidor Final | E66: Gerson | F66: pica suave | G66: =SUMIFS(Product!$D$5:$D$24,Product!$C$5:$C$24,Venta!F63) -> 130 | H66: 1 | I66: =G66*H66 -> 130 | J66: Transferencia | L66: Directo
B67: semana 4 | C67: 46180 | D67: Consumidor Final | E67: Nicolle | F67: Pica suave | G67: =SUMIFS(Product!$D$5:$D$24,Product!$C$5:$C$24,Venta!F67) -> 130 | H67: 1 | I67: =G67*H67 -> 130 | J67: Transferencia | L67: Directo
B68: semana 5 | C68: 46183 | D68: Consumidor Final | E68: Nicolle | F68: Combo | G68: =SUMIFS(Product!$D$5:$D$24,Product!$C$5:$C$24,Venta!F69) -> 180 | H68: 1 | I68: =G68*H68 -> 180 | J68: Transferencia | L68: Directo
B69: semana 5 | C69: 46185 | D69: Consumidor Final | E69: Nicolle | F69: Combo | G69: =SUMIFS(Product!$D$5:$D$24,Product!$C$5:$C$24,Venta!F70) -> 180 | H69: 1 | I69: =G69*H69 -> 180 | J69: Transferencia | K69: Extremo grande, suave pequeño | L69: Directo
B70: semana 5 | C70: 46184 | D70: Consumidor Final | E70: Gerson | F70: Combo | G70: =SUMIFS(Product!$D$5:$D$24,Product!$C$5:$C$24,Venta!F71) -> 180 | H70: 1 | I70: =G70*H70 -> 180 | J70: Transferencia | K70: Pikarico grande, suave pequeño | L70: Directo
B71: semana 5 | C71: 46186 | D71: Consumidor Final | E71: Gerson | F71: Combo | G71: =SUMIFS(Product!$D$5:$D$24,Product!$C$5:$C$24,Venta!F72) -> 180 | H71: 2 | I71: =G71*H71 -> 360 | J71: Transferencia | K71: los dos extremos | L71: Directo
B72: semana 5 | C72: 46183 | D72: Consumidor Final | E72: keren | F72: Combo | G72: =SUMIFS(Product!$D$5:$D$24,Product!$C$5:$C$24,Venta!F72) -> 180 | H72: 1 | I72: =G72*H72 -> 180 | J72: Transferencia | K72: extremo grande, rico pequeño | L72: Directo
B73: semana 5 | C73: 46186 | D73: Consumidor Final | E73: Gerson | F73: Pica extremo | G73: =SUMIFS(Product!$D$5:$D$24,Product!$C$5:$C$24,Venta!F74) -> 130 | H73: 1 | I73: =G73*H73 -> 130 | J73: Transferencia | L73: Intermediario (Cargo expreso)
B74: semana 5 | C74: 46181 | D74: Consumidor Final | E74: Gerson | F74: Pica extremo | G74: =SUMIFS(Product!$D$5:$D$24,Product!$C$5:$C$24,Venta!F84) -> 130 | H74: 1 | I74: =G74*H74 -> 130 | J74: Transferencia | L74: Directo
B75: semana 5 | C75: 46186 | D75: Consumidor Final | E75: Tomas | F75: Pica extremo | G75: =SUMIFS(Product!$D$5:$D$24,Product!$C$5:$C$24,Venta!F77) -> 130 | H75: 6 | I75: =G75*H75 -> 780 | J75: Transferencia | L75: Directo
B76: semana 5 | C76: 46182 | D76: Consumidor Final | E76: Sthepany | F76: Pica extremo | G76: =SUMIFS(Product!$D$5:$D$24,Product!$C$5:$C$24,Venta!F78) -> 130 | H76: 3 | I76: =G76*H76 -> 390 | J76: Transferencia | L76: Directo
B77: semana 5 | C77: 46186 | D77: Consumidor Final | E77: Alexandra | F77: Pica extremo | G77: =SUMIFS(Product!$D$5:$D$24,Product!$C$5:$C$24,Venta!F85) -> 130 | H77: 2 | I77: =G77*H77 -> 260 | J77: efectivo | L77: Directo
B78: semana 5 | C78: 46186 | D78: Consumidor Final | E78: Alexandra | F78: Pica extremo | G78: =SUMIFS(Product!$D$5:$D$24,Product!$C$5:$C$24,Venta!F88) -> 130 | H78: 2 | I78: =G78*H78 -> 260 | J78: Transferencia | L78: Directo
B79: semana 5 | C79: 46186 | D79: Consumidor Final | E79: Alexandra | F79: Pica extremo | G79: =SUMIFS(Product!$D$5:$D$24,Product!$C$5:$C$24,Venta!F91) -> 130 | H79: 1 | I79: =G79*H79 -> 130 | J79: credito | L79: Directo
B80: semana 5 | C80: 46186 | D80: Consumidor Final | E80: Gerson | F80: Pica rico | G80: =SUMIFS(Product!$D$5:$D$24,Product!$C$5:$C$24,Venta!F73) -> 130 | H80: 1 | I80: =G80*H80 -> 130 | J80: Transferencia | L80: Directo
B81: semana 5 | C81: 46185 | D81: Consumidor Final | E81: Gerson | F81: Pica rico | G81: =SUMIFS(Product!$D$5:$D$24,Product!$C$5:$C$24,Venta!F75) -> 130 | H81: 1 | I81: =G81*H81 -> 130 | J81: Transferencia | L81: Directo
B82: semana 5 | C82: 46182 | D82: Consumidor Final | E82: Sthepany | F82: Pica rico | G82: =SUMIFS(Product!$D$5:$D$24,Product!$C$5:$C$24,Venta!F79) -> 130 | H82: 1 | I82: =G82*H82 -> 130 | J82: Transferencia | K82: los dos extremos | L82: Directo
B83: semana 5 | C83: 46183 | D83: Consumidor Final | E83: keren | F83: Pica rico | G83: =SUMIFS(Product!$D$5:$D$24,Product!$C$5:$C$24,Venta!F81) -> 130 | H83: 1 | I83: =G83*H83 -> 130 | J83: Transferencia | L83: Directo
B84: semana 5 | C84: 46186 | D84: Consumidor Final | E84: keren | F84: Pica rico | G84: =SUMIFS(Product!$D$5:$D$24,Product!$C$5:$C$24,Venta!F92) -> 130 | H84: 1 | I84: =G84*H84 -> 130 | J84: Transferencia | L84: Directo
B85: semana 5 | C85: 46181 | D85: Consumidor Final | E85: Gerson | F85: Pica rico | G85: =SUMIFS(Product!$D$5:$D$24,Product!$C$5:$C$24,Venta!F83) -> 130 | H85: 1 | I85: =G85*H85 -> 130 | J85: Transferencia | L85: Directo
B86: semana 5 | C86: 46186 | D86: Consumidor Final | E86: Alexandra | F86: Pica rico | G86: =SUMIFS(Product!$D$5:$D$24,Product!$C$5:$C$24,Venta!F87) -> 130 | H86: 1 | I86: =G86*H86 -> 130 | J86: efectivo | L86: Directo
B87: semana 5 | C87: 46186 | D87: Consumidor Final | E87: Alexandra | F87: Pica rico | G87: =SUMIFS(Product!$D$5:$D$24,Product!$C$5:$C$24,Venta!F89) -> 130 | H87: 5 | I87: =G87*H87 -> 650 | J87: Transferencia | L87: Directo
B88: semana 5 | C88: 46186 | D88: Carlos Hernandez | E88: keren | F88: pica rico | G88: =SUMIFS(Product!$D$5:$D$24,Product!$C$5:$C$24,Venta!F88) -> 130 | H88: 1 | I88: =G88*H88 -> 130 | J88: Transferencia | L88: Directo
B89: semana 5 | C89: 46186 | D89: Carlos Hernandez | E89: Nicolle | F89: pica suave | G89: =SUMIFS(Product!$D$5:$D$24,Product!$C$5:$C$24,Venta!F89) -> 130 | H89: 1 | I89: =G89*H89 -> 130 | J89: Transferencia | L89: Directo
B90: semana 5 | C90: 46185 | D90: Consumidor Final | E90: Gerson | F90: Pica suave | G90: =SUMIFS(Product!$D$5:$D$24,Product!$C$5:$C$24,Venta!F76) -> 130 | H90: 1 | I90: =G90*H90 -> 130 | J90: Transferencia | L90: Directo
B91: semana 5 | C91: 46186 | D91: Consumidor Final | E91: Alexandra | F91: pica suave | G91: =SUMIFS(Product!$D$5:$D$24,Product!$C$5:$C$24,Venta!F86) -> 130 | H91: 2 | I91: =G91*H91 -> 260 | J91: efectivo | L91: Directo
B92: semana 5 | C92: 46186 | D92: Consumidor Final | E92: Alexandra | F92: pica suave | G92: =SUMIFS(Product!$D$5:$D$24,Product!$C$5:$C$24,Venta!F90) -> 130 | H92: 1 | I92: =G92*H92 -> 130 | J92: credito | L92: Directo
B93: semana 5 | C93: 46184 | D93: Consumidor Final | E93: keren | F93: pica suave | G93: =SUMIFS(Product!$D$5:$D$24,Product!$C$5:$C$24,Venta!F80) -> 130 | H93: 1 | I93: =G93*H93 -> 130 | J93: Transferencia | L93: Directo
B94: Semana 6 | C94: 46188 | D94: Consumidor Final | E94: Tomas | F94: pica rico pequeño | G94: =SUMIFS(Product!$D$5:$D$24,Product!$C$5:$C$24,Venta!F94) -> 70 | H94: 10 | I94: =G94*H94 -> 700 | J94: efectivo | L94: Directo
B95: semana 6 | C95: 46188 | D95: Consumidor Final | E95: Tomas | F95: pica extremo pequeño | G95: =SUMIFS(Product!$D$5:$D$24,Product!$C$5:$C$24,Venta!F95) -> 70 | H95: 5 | I95: =G95*H95 -> 350 | J95: efectivo | L95: Directo
B96: Semana 6 | C96: 46188 | D96: Consumidor Final | E96: Tomas | F96: Combo | G96: =SUMIFS(Product!$D$5:$D$24,Product!$C$5:$C$24,Venta!F96) -> 180 | H96: 2 | I96: =G96*H96 -> 360 | J96: efectivo | K96: suave grande, extremo pequeño | L96: Directo
B97: Semana 6 | C97: 46188 | D97: Consumidor Final | E97: Tomas | F97: Pica extremo | G97: =SUMIFS(Product!$D$5:$D$24,Product!$C$5:$C$24,Venta!F97) -> 130 | H97: 1 | I97: =G97*H97 -> 130 | J97: efectivo | L97: Directo
B98: Semana 6 | C98: 46188 | D98: melvin indufesa | E98: Nicolle | F98: Pica extremo | G98: =SUMIFS(Product!$D$5:$D$24,Product!$C$5:$C$24,Venta!F98) -> 130 | H98: 1 | I98: =G98*H98 -> 130 | J98: efectivo | L98: Directo
B99: Semana 6 | C99: 46188 | D99: hever perdomo | E99: Nicolle | F99: pica extremo | G99: =SUMIFS(Product!$D$5:$D$24,Product!$C$5:$C$24,Venta!F99) -> 130 | H99: 1 | I99: =G99*H99 -> 130 | J99: efectivo | L99: Directo
B100: Semana 6 | C100: 46188 | D100: estefany meza | E100: Nicolle | F100: pica extremo | G100: =SUMIFS(Product!$D$5:$D$24,Product!$C$5:$C$24,Venta!F100) -> 130 | H100: 1 | I100: =G100*H100 -> 130 | J100: Transferencia | L100: Directo
B101: Semana 6 | C101: 46189 | D101: keily vargas | E101: Nicolle | F101: Combo | G101: =SUMIFS(Product!$D$5:$D$24,Product!$C$5:$C$24,Venta!F101) -> 180 | H101: 1 | I101: =G101*H101 -> 180 | J101: Transferencia | K101: extremo,extremo | L101: Directo
...

Sheet Venta Semana
B1: INFORME DE VENTAS POR PRODUCTO UNIDADES
B2: Item | C2: Producto | D2: Semana 3 | E2: Semana 4 | F2: semana 5 | G2: Semana 6 | H2: Semana 7 | I2: Semana 8 | J2: Semana 9 | K2: Semana 10 | L2: Semana 11 | M2: Semana 12 | N2: Total
B3: 1 | C3: =Product!C5 -> Pica extremo | D3: =SUMIFS(Venta!$I$4:$I$365,Venta!$F$4:$F$365,'Venta Semana'!C3,Venta!$B$4:$B$365,'Venta Semana'!$D$2)/(130) -> 43 | E3: =SUMIFS(Venta!$I$4:$I$365,Venta!$F$4:$F$365,'Venta Semana'!C3,Venta!$B$4:$B$365,'Venta Semana'!$E$12)/(130) -> 10 | F3: =SUMIFS(Venta!$I$4:$I$365,Venta!$F$4:$F$365,'Venta Semana'!C3,Venta!$B$4:$B$365,'Venta Semana'!$F$12)/(130) -> 16 | G3: =SUMIFS(Venta!$I$4:$I$365,Venta!$F$4:$F$365,'Venta Semana'!C3,Venta!$B$4:$B$365,'Venta Semana'!$G$12)/(130) -> 10 | H3: =SUMIFS(Venta!$I$4:$I$365,Venta!$F$4:$F$365,'Venta Semana'!C3,Venta!$B$4:$B$365,'Venta Semana'!$H$12)/(130) -> 0 | I3: =SUMIFS(Venta!$I$4:$I$365,Venta!$F$4:$F$365,'Venta Semana'!C3,Venta!$B$4:$B$365,'Venta Semana'!$I$12) -> 0 | J3: =SUMIFS(Venta!$I$4:$I$365,Venta!$F$4:$F$365,'Venta Semana'!C3,Venta!$B$4:$B$365,'Venta Semana'!$J$12) -> 0 | K3: =SUMIFS(Venta!$I$4:$I$365,Venta!$F$4:$F$365,'Venta Semana'!C3,Venta!$B$4:$B$365,'Venta Semana'!$K$12) -> 0 | L3: =SUMIFS(Venta!$I$4:$I$365,Venta!$F$4:$F$365,'Venta Semana'!C3,Venta!$B$4:$B$365,'Venta Semana'!$L$12) -> 0 | M3: =SUMIFS(Venta!$I$4:$I$365,Venta!$F$4:$F$365,'Venta Semana'!C3,Venta!$B$4:$B$365,'Venta Semana'!$M$12) -> 0 | N3: =SUM(D3:M3) -> 79
B4: 2 | C4: =Product!C6 -> Pica rico | D4: =SUMIFS(Venta!$I$4:$I$365,Venta!$F$4:$F$365,'Venta Semana'!C4,Venta!$B$4:$B$365,'Venta Semana'!$D$12)/(130) -> 22 | E4: =SUMIFS(Venta!$I$4:$I$365,Venta!$F$4:$F$365,'Venta Semana'!C4,Venta!$B$4:$B$365,'Venta Semana'!$E$12)/(130) -> 16 | F4: =SUMIFS(Venta!$I$4:$I$365,Venta!$F$4:$F$365,'Venta Semana'!C4,Venta!$B$4:$B$365,'Venta Semana'!$F$12)/(130) -> 13 | G4: =SUMIFS(Venta!$I$4:$I$365,Venta!$F$4:$F$365,'Venta Semana'!C4,Venta!$B$4:$B$365,'Venta Semana'!$G$12)/(130) -> 4 | H4: =SUMIFS(Venta!$I$4:$I$365,Venta!$F$4:$F$365,'Venta Semana'!C4,Venta!$B$4:$B$365,'Venta Semana'!$H$12)/(130) -> 0 | I4: =SUMIFS(Venta!$I$4:$I$365,Venta!$F$4:$F$365,'Venta Semana'!C4,Venta!$B$4:$B$365,'Venta Semana'!$I$12) -> 0 | J4: =SUMIFS(Venta!$I$4:$I$365,Venta!$F$4:$F$365,'Venta Semana'!C4,Venta!$B$4:$B$365,'Venta Semana'!$J$12) -> 0 | K4: =SUMIFS(Venta!$I$4:$I$365,Venta!$F$4:$F$365,'Venta Semana'!C4,Venta!$B$4:$B$365,'Venta Semana'!$K$12) -> 0 | L4: =SUMIFS(Venta!$I$4:$I$365,Venta!$F$4:$F$365,'Venta Semana'!C4,Venta!$B$4:$B$365,'Venta Semana'!$L$12) -> 0 | M4: =SUMIFS(Venta!$I$4:$I$365,Venta!$F$4:$F$365,'Venta Semana'!C4,Venta!$B$4:$B$365,'Venta Semana'!$M$12) -> 0 | N4: =SUM(D4:M4) -> 55
B5: 3 | C5: =Product!C7 -> Pica suave | D5: =SUMIFS(Venta!$I$4:$I$365,Venta!$F$4:$F$365,'Venta Semana'!C5,Venta!$B$4:$B$365,'Venta Semana'!$D$12)/(130) -> 15 | E5: =SUMIFS(Venta!$I$4:$I$365,Venta!$F$4:$F$365,'Venta Semana'!C5,Venta!$B$4:$B$365,'Venta Semana'!$E$12)/(130) -> 16 | F5: =SUMIFS(Venta!$I$4:$I$365,Venta!$F$4:$F$365,'Venta Semana'!C5,Venta!$B$4:$B$365,'Venta Semana'!$F$12)/(130) -> 6 | G5: =SUMIFS(Venta!$I$4:$I$365,Venta!$F$4:$F$365,'Venta Semana'!C5,Venta!$B$4:$B$365,'Venta Semana'!$G$12)/(130) -> 3 | H5: =SUMIFS(Venta!$I$4:$I$365,Venta!$F$4:$F$365,'Venta Semana'!C5,Venta!$B$4:$B$365,'Venta Semana'!$H$12)/(130) -> 0 | I5: =SUMIFS(Venta!$I$4:$I$365,Venta!$F$4:$F$365,'Venta Semana'!C5,Venta!$B$4:$B$365,'Venta Semana'!$I$12) -> 0 | J5: =SUMIFS(Venta!$I$4:$I$365,Venta!$F$4:$F$365,'Venta Semana'!C5,Venta!$B$4:$B$365,'Venta Semana'!$J$12) -> 0 | K5: =SUMIFS(Venta!$I$4:$I$365,Venta!$F$4:$F$365,'Venta Semana'!C5,Venta!$B$4:$B$365,'Venta Semana'!$K$12) -> 0 | L5: =SUMIFS(Venta!$I$4:$I$365,Venta!$F$4:$F$365,'Venta Semana'!C5,Venta!$B$4:$B$365,'Venta Semana'!$L$12) -> 0 | M5: =SUMIFS(Venta!$I$4:$I$365,Venta!$F$4:$F$365,'Venta Semana'!C5,Venta!$B$4:$B$365,'Venta Semana'!$M$12) -> 0 | N5: =SUM(D5:M5) -> 40
B6: 4 | C6: =Product!C8 -> Combo | D6: =SUMIFS(Venta!$I$4:$I$365,Venta!$F$4:$F$365,'Venta Semana'!C6,Venta!$B$4:$B$365,'Venta Semana'!$D$12)/(130) -> 0 | E6: =SUMIFS(Venta!$I$4:$I$365,Venta!$F$4:$F$365,'Venta Semana'!C6,Venta!$B$4:$B$365,'Venta Semana'!$E$12)/(130) -> 0 | F6: =SUMIFS(Venta!$I$4:$I$365,Venta!$F$4:$F$365,'Venta Semana'!C6,Venta!$B$4:$B$365,'Venta Semana'!$F$12)/(180) -> 6 | G6: =SUMIFS(Venta!$I$4:$I$365,Venta!$F$4:$F$365,'Venta Semana'!C6,Venta!$B$4:$B$365,'Venta Semana'!$G$12)/(180) -> 8
B7: 5 | C7: =Product!C9 -> pica extremo pequeño | D7: =SUMIFS(Venta!$I$4:$I$365,Venta!$F$4:$F$365,'Venta Semana'!C7,Venta!$B$4:$B$365,'Venta Semana'!$D$12)/(130) -> 0 | E7: =SUMIFS(Venta!$I$4:$I$365,Venta!$F$4:$F$365,'Venta Semana'!C7,Venta!$B$4:$B$365,'Venta Semana'!$E$12)/(130) -> 0 | G7: =SUMIFS(Venta!$I$4:$I$365,Venta!$F$4:$F$365,'Venta Semana'!C7,Venta!$B$4:$B$365,'Venta Semana'!$G$12)/(70) -> 5
B8: 6 | C8: =Product!C10 -> pica rico pequeño | D8: =SUMIFS(Venta!$I$4:$I$365,Venta!$F$4:$F$365,'Venta Semana'!C8,Venta!$B$4:$B$365,'Venta Semana'!$D$12)/(130) -> 0 | E8: =SUMIFS(Venta!$I$4:$I$365,Venta!$F$4:$F$365,'Venta Semana'!C8,Venta!$B$4:$B$365,'Venta Semana'!$E$12)/(130) -> 0 | G8: =SUMIFS(Venta!$I$4:$I$365,Venta!$F$4:$F$365,'Venta Semana'!C8,Venta!$B$4:$B$365,'Venta Semana'!$G$12)/(70) -> 10
C9: Total Venta unidades | D9: =SUM(D3:D5) -> 80 | E9: =SUM(E3:E5) -> 42 | F9: =SUM(F3:F6) -> 41 | G9: =SUM(G3:G8) -> 40 | H9: =SUM(H3:H5) -> 0 | I9: =SUM(I3:I5) -> 0 | J9: =SUM(J3:J5) -> 0 | K9: =SUM(K3:K5) -> 0 | L9: =SUM(L3:L5) -> 0 | M9: =SUM(M3:M5) -> 0 | N9: =SUM(D9:M9) -> 203
B11: INFORME DE VENTAS POR PRODUCTO MES A MES
B12: Item | C12: Producto | D12: semana 3 | E12: semana 4 | F12: semana 5 | G12: semana 6 | H12: semana 7 | I12: semana 8 | J12: semana 9 | K12: semana 10 | L12: semana 11 | M12: semana 12 | N12: Total
B13: 1 | C13: =Product!C5 -> Pica extremo | D13: =SUMIFS(Venta!$I$4:$I$365,Venta!$F$4:$F$365,'Venta Semana'!C13,Venta!$B$4:$B$365,'Venta Semana'!$D$12) -> 5590 | E13: =SUMIFS(Venta!$I$4:$I$365,Venta!$F$4:$F$365,'Venta Semana'!C13,Venta!$B$4:$B$365,'Venta Semana'!$E$12) -> 1300 | F13: =SUMIFS(Venta!$I$4:$I$365,Venta!$F$4:$F$365,'Venta Semana'!C13,Venta!$B$4:$B$365,'Venta Semana'!$F$12) -> 2080 | G13: =SUMIFS(Venta!$I$4:$I$365,Venta!$F$4:$F$365,'Venta Semana'!C13,Venta!$B$4:$B$365,'Venta Semana'!$G$12) -> 1300 | H13: =SUMIFS(Venta!$I$4:$I$365,Venta!$F$4:$F$365,'Venta Semana'!C13,Venta!$B$4:$B$365,'Venta Semana'!$H$12) -> 0 | I13: =SUMIFS(Venta!$I$4:$I$365,Venta!$F$4:$F$365,'Venta Semana'!C13,Venta!$B$4:$B$365,'Venta Semana'!$I$12) -> 0 | J13: =SUMIFS(Venta!$I$4:$I$365,Venta!$F$4:$F$365,'Venta Semana'!C13,Venta!$B$4:$B$365,'Venta Semana'!$J$12) -> 0 | K13: =SUMIFS(Venta!$I$4:$I$365,Venta!$F$4:$F$365,'Venta Semana'!C13,Venta!$B$4:$B$365,'Venta Semana'!$K$12) -> 0 | L13: =SUMIFS(Venta!$I$4:$I$365,Venta!$F$4:$F$365,'Venta Semana'!C13,Venta!$B$4:$B$365,'Venta Semana'!$L$12) -> 0 | M13: =SUMIFS(Venta!$I$4:$I$365,Venta!$F$4:$F$365,'Venta Semana'!C13,Venta!$B$4:$B$365,'Venta Semana'!$M$12) -> 0 | N13: =SUM(D13:M13) -> 10270
B14: 2 | C14: =Product!C6 -> Pica rico | D14: =SUMIFS(Venta!$I$4:$I$365,Venta!$F$4:$F$365,'Venta Semana'!C14,Venta!$B$4:$B$365,'Venta Semana'!$D$12) -> 2860 | E14: =SUMIFS(Venta!$I$4:$I$365,Venta!$F$4:$F$365,'Venta Semana'!C14,Venta!$B$4:$B$365,'Venta Semana'!$E$12) -> 2080 | F14: =SUMIFS(Venta!$I$4:$I$365,Venta!$F$4:$F$365,'Venta Semana'!C14,Venta!$B$4:$B$365,'Venta Semana'!$F$12) -> 1690 | G14: =SUMIFS(Venta!$I$4:$I$365,Venta!$F$4:$F$365,'Venta Semana'!C14,Venta!$B$4:$B$365,'Venta Semana'!$G$12) -> 520 | H14: =SUMIFS(Venta!$I$4:$I$365,Venta!$F$4:$F$365,'Venta Semana'!C14,Venta!$B$4:$B$365,'Venta Semana'!$H$12) -> 0 | I14: =SUMIFS(Venta!$I$4:$I$365,Venta!$F$4:$F$365,'Venta Semana'!C14,Venta!$B$4:$B$365,'Venta Semana'!$I$12) -> 0 | J14: =SUMIFS(Venta!$I$4:$I$365,Venta!$F$4:$F$365,'Venta Semana'!C14,Venta!$B$4:$B$365,'Venta Semana'!$J$12) -> 0 | K14: =SUMIFS(Venta!$I$4:$I$365,Venta!$F$4:$F$365,'Venta Semana'!C14,Venta!$B$4:$B$365,'Venta Semana'!$K$12) -> 0 | L14: =SUMIFS(Venta!$I$4:$I$365,Venta!$F$4:$F$365,'Venta Semana'!C14,Venta!$B$4:$B$365,'Venta Semana'!$L$12) -> 0 | M14: =SUMIFS(Venta!$I$4:$I$365,Venta!$F$4:$F$365,'Venta Semana'!C14,Venta!$B$4:$B$365,'Venta Semana'!$M$12) -> 0 | N14: =SUM(D14:M14) -> 7150
B15: 3 | C15: =Product!C7 -> Pica suave | D15: =SUMIFS(Venta!$I$4:$I$365,Venta!$F$4:$F$365,'Venta Semana'!C15,Venta!$B$4:$B$365,'Venta Semana'!$D$12) -> 1950 | E15: =SUMIFS(Venta!$I$4:$I$365,Venta!$F$4:$F$365,'Venta Semana'!C15,Venta!$B$4:$B$365,'Venta Semana'!$E$12) -> 2080 | F15: =SUMIFS(Venta!$I$4:$I$365,Venta!$F$4:$F$365,'Venta Semana'!C15,Venta!$B$4:$B$365,'Venta Semana'!$F$12) -> 780 | G15: =SUMIFS(Venta!$I$4:$I$365,Venta!$F$4:$F$365,'Venta Semana'!C15,Venta!$B$4:$B$365,'Venta Semana'!$G$12) -> 390 | H15: =SUMIFS(Venta!$I$4:$I$365,Venta!$F$4:$F$365,'Venta Semana'!C15,Venta!$B$4:$B$365,'Venta Semana'!$H$12) -> 0 | I15: =SUMIFS(Venta!$I$4:$I$365,Venta!$F$4:$F$365,'Venta Semana'!C15,Venta!$B$4:$B$365,'Venta Semana'!$I$12) -> 0 | J15: =SUMIFS(Venta!$I$4:$I$365,Venta!$F$4:$F$365,'Venta Semana'!C15,Venta!$B$4:$B$365,'Venta Semana'!$J$12) -> 0 | K15: =SUMIFS(Venta!$I$4:$I$365,Venta!$F$4:$F$365,'Venta Semana'!C15,Venta!$B$4:$B$365,'Venta Semana'!$K$12) -> 0 | L15: =SUMIFS(Venta!$I$4:$I$365,Venta!$F$4:$F$365,'Venta Semana'!C15,Venta!$B$4:$B$365,'Venta Semana'!$L$12) -> 0 | M15: =SUMIFS(Venta!$I$4:$I$365,Venta!$F$4:$F$365,'Venta Semana'!C15,Venta!$B$4:$B$365,'Venta Semana'!$M$12) -> 0 | N15: =SUM(D15:M15) -> 5200
B16: 4 | C16: =Product!C8 -> Combo | D16: =SUMIFS(Venta!$I$4:$I$365,Venta!$F$4:$F$365,'Venta Semana'!C16,Venta!$B$4:$B$365,'Venta Semana'!$D$12) -> 0 | E16: =SUMIFS(Venta!$I$4:$I$365,Venta!$F$4:$F$365,'Venta Semana'!C16,Venta!$B$4:$B$365,'Venta Semana'!$E$12) -> 0 | F16: =SUMIFS(Venta!$I$4:$I$365,Venta!$F$4:$F$365,'Venta Semana'!C16,Venta!$B$4:$B$365,'Venta Semana'!$F$12) -> 1080 | G16: =SUMIFS(Venta!$I$4:$I$365,Venta!$F$4:$F$365,'Venta Semana'!C16,Venta!$B$4:$B$365,'Venta Semana'!$G$12) -> 1440 | H16: =SUMIFS(Venta!$I$4:$I$365,Venta!$F$4:$F$365,'Venta Semana'!C16,Venta!$B$4:$B$365,'Venta Semana'!$H$12) -> 0 | I16: =SUMIFS(Venta!$I$4:$I$365,Venta!$F$4:$F$365,'Venta Semana'!C16,Venta!$B$4:$B$365,'Venta Semana'!$I$12) -> 0 | J16: =SUMIFS(Venta!$I$4:$I$365,Venta!$F$4:$F$365,'Venta Semana'!C16,Venta!$B$4:$B$365,'Venta Semana'!$J$12) -> 0 | K16: =SUMIFS(Venta!$I$4:$I$365,Venta!$F$4:$F$365,'Venta Semana'!C16,Venta!$B$4:$B$365,'Venta Semana'!$K$12) -> 0 | L16: =SUMIFS(Venta!$I$4:$I$365,Venta!$F$4:$F$365,'Venta Semana'!C16,Venta!$B$4:$B$365,'Venta Semana'!$L$12) -> 0 | M16: =SUMIFS(Venta!$I$4:$I$365,Venta!$F$4:$F$365,'Venta Semana'!C16,Venta!$B$4:$B$365,'Venta Semana'!$M$12) -> 0
B17: 5 | C17: =Product!C9 -> pica extremo pequeño | D17: =SUMIFS(Venta!$I$4:$I$365,Venta!$F$4:$F$365,'Venta Semana'!C17,Venta!$B$4:$B$365,'Venta Semana'!$D$12) -> 0 | E17: =SUMIFS(Venta!$I$4:$I$365,Venta!$F$4:$F$365,'Venta Semana'!C17,Venta!$B$4:$B$365,'Venta Semana'!$E$12) -> 0 | F17: =SUMIFS(Venta!$I$4:$I$365,Venta!$F$4:$F$365,'Venta Semana'!C17,Venta!$B$4:$B$365,'Venta Semana'!$F$12) -> 0 | G17: =SUMIFS(Venta!$I$4:$I$365,Venta!$F$4:$F$365,'Venta Semana'!C17,Venta!$B$4:$B$365,'Venta Semana'!$G$12) -> 350 | H17: =SUMIFS(Venta!$I$4:$I$365,Venta!$F$4:$F$365,'Venta Semana'!C17,Venta!$B$4:$B$365,'Venta Semana'!$H$12) -> 0 | I17: =SUMIFS(Venta!$I$4:$I$365,Venta!$F$4:$F$365,'Venta Semana'!C17,Venta!$B$4:$B$365,'Venta Semana'!$I$12) -> 0 | J17: =SUMIFS(Venta!$I$4:$I$365,Venta!$F$4:$F$365,'Venta Semana'!C17,Venta!$B$4:$B$365,'Venta Semana'!$J$12) -> 0 | K17: =SUMIFS(Venta!$I$4:$I$365,Venta!$F$4:$F$365,'Venta Semana'!C17,Venta!$B$4:$B$365,'Venta Semana'!$K$12) -> 0 | L17: =SUMIFS(Venta!$I$4:$I$365,Venta!$F$4:$F$365,'Venta Semana'!C17,Venta!$B$4:$B$365,'Venta Semana'!$L$12) -> 0 | M17: =SUMIFS(Venta!$I$4:$I$365,Venta!$F$4:$F$365,'Venta Semana'!C17,Venta!$B$4:$B$365,'Venta Semana'!$M$12) -> 0
B18: 6 | C18: =Product!C10 -> pica rico pequeño | D18: =SUMIFS(Venta!$I$4:$I$365,Venta!$F$4:$F$365,'Venta Semana'!C18,Venta!$B$4:$B$365,'Venta Semana'!$D$12) -> 0 | E18: =SUMIFS(Venta!$I$4:$I$365,Venta!$F$4:$F$365,'Venta Semana'!C18,Venta!$B$4:$B$365,'Venta Semana'!$E$12) -> 0 | F18: =SUMIFS(Venta!$I$4:$I$365,Venta!$F$4:$F$365,'Venta Semana'!C18,Venta!$B$4:$B$365,'Venta Semana'!$F$12) -> 0 | G18: =SUMIFS(Venta!$I$4:$I$365,Venta!$F$4:$F$365,'Venta Semana'!C18,Venta!$B$4:$B$365,'Venta Semana'!$G$12) -> 700 | H18: =SUMIFS(Venta!$I$4:$I$365,Venta!$F$4:$F$365,'Venta Semana'!C18,Venta!$B$4:$B$365,'Venta Semana'!$H$12) -> 0 | I18: =SUMIFS(Venta!$I$4:$I$365,Venta!$F$4:$F$365,'Venta Semana'!C18,Venta!$B$4:$B$365,'Venta Semana'!$I$12) -> 0 | J18: =SUMIFS(Venta!$I$4:$I$365,Venta!$F$4:$F$365,'Venta Semana'!C18,Venta!$B$4:$B$365,'Venta Semana'!$J$12) -> 0 | K18: =SUMIFS(Venta!$I$4:$I$365,Venta!$F$4:$F$365,'Venta Semana'!C18,Venta!$B$4:$B$365,'Venta Semana'!$K$12) -> 0 | L18: =SUMIFS(Venta!$I$4:$I$365,Venta!$F$4:$F$365,'Venta Semana'!C18,Venta!$B$4:$B$365,'Venta Semana'!$L$12) -> 0 | M18: =SUMIFS(Venta!$I$4:$I$365,Venta!$F$4:$F$365,'Venta Semana'!C18,Venta!$B$4:$B$365,'Venta Semana'!$M$12) -> 0
C19: Total venta | D19: =SUM(D13:D15) -> 10400 | E19: =SUM(E13:E15) -> 5460 | F19: =SUM(F13:F16) -> 5630 | G19: =SUM(G13:G18) -> 4700 | H19: =SUM(H13:H15) -> 0 | I19: =SUM(I13:I15) -> 0 | J19: =SUM(J13:J15) -> 0 | K19: =SUM(K13:K15) -> 0 | L19: =SUM(L13:L15) -> 0 | M19: =SUM(M13:M15) -> 0 | N19: =SUM(D19:M19) -> 26190

Sheet Venta por Vendedor
B2: INFORME DE VENTAS POR VENDEDOR
B3: Semana 3
B4: Vendedor | C4: pica extremo | D4: pica rico | E4: pica suave | I4: SUBTOTAL | J4: TOTAL
B5: Alexandra | C5: 6 | D5: 6 | E5: 5 | I5: =SUM(C5:E5) -> 17 | J5: =SUM(I5:I10) -> 51
B6: Gerson | C6: 0 | D6: =Venta!H34 -> 1 | E6: 0 | I6: =SUM(C6:E6) -> 1
B7: Keren | C7: =Venta!H10 -> 1 | D7: 0 | E7: 2 | I7: =SUM(C7:E7) -> 3
B8: Nicolle | C8: 13 | D8: 4 | E8: 3 | I8: =SUM(C8:E8) -> 20 | K8: NOTA: EN LA SEMANA 3 NO SE ESTAN TOMANDO EN CUENTA LOS VENDIDOS 29 EN LANZAMIENTOS SOLO LOS INDIVIDUALES
B9: Sthepany | C9: =Venta!H38 -> 5 | D9: 1 | I9: =SUM(C9:E9) -> 6
B10: Tomas | C10: 3 | E10: 1 | I10: =SUM(C10:E10) -> 4
B11: Semana 4
B12: Vendedor | C12: pica extremo | D12: pica rico | E12: pica suave | I12: SUBTOTAL | J12: TOTAL
B13: Alexandra | I13: =SUM(C13:E13) -> 0 | J13: =SUM(I13:I18) -> 42
B14: Gerson | C14: 2 | D14: 3 | E14: 2 | I14: =SUM(C14:E14) -> 7
B15: Keren | C15: 2 | D15: 3 | E15: 6 | I15: =SUM(C15:E15) -> 11
B16: Nicolle | C16: 1 | E16: 1 | I16: =SUM(C16:E16) -> 2
B17: Sthepany | C17: 3 | D17: 2 | E17: 1 | I17: =SUM(C17:E17) -> 6
B18: Tomas | C18: 2 | D18: 8 | E18: 6 | I18: =SUM(C18:E18) -> 16
B19: SEMANA 5
B20: Vendedor | C20: pica extremo | D20: pica rico | E20: pica suave | H20: SUB UNIDADES | I20: COMBO | J20: TOTAL
B21: Alexandra | C21: 5 | D21: 6 | E21: 3 | H21: =SUM(C21:E21) -> 14
B22: Gerson | C22: 2 | D22: 3 | E22: 1 | H22: =SUM(C22:K22) -> 9 | I22: 3
B23: Keren | D23: 3 | E23: 1 | H23: =SUM(C23:K23) -> 5 | I23: 1
B24: Nicolle | E24: 1 | H24: =SUM(C24:K24) -> 3 | I24: 2
B25: Sthepany | C25: 3 | D25: 1 | H25: =SUM(C25:K25) -> 4
B26: Tomas | C26: 6 | H26: =SUM(C26:K26) -> 6
B27: TOTAL | C27: =SUM(C21:C26) -> 16 | D27: =SUM(D21:D26) -> 13 | E27: =SUM(E21:E26) -> 6 | H27: =SUM(H21:H26) -> 16 | I27: =SUM(I21:I26) -> 6 | J27: =SUM(I27+H27) -> 41
B28: SEMANA 6
B29: Vendedor | C29: pica extremo | D29: pica rico | E29: pica suave | F29: Extremo pequeño | G29: Rico pequeño | H29: Combo | I29: SUBTOTAL | J29: TOTAL
B30: Alexandra | C30: 2 | E30: 2 | I30: =SUM(C30:G30) -> 4
B31: Gerson | H31: 1 | I31: =SUM(C31:G31) -> 0
B32: Keren | H32: 2 | I32: =SUM(C32:G32) -> 0
B33: Nicolle | C33: 3 | H33: 2 | I33: =SUM(C33:G33) -> 3
B34: Sthepany | D34: 2 | H34: 1 | I34: =SUM(C34:G34) -> 2
B35: Tomas | C35: 1 | F35: 5 | G35: 10 | H35: 2 | I35: =SUM(C35:G35) -> 16
B36: TOTAL | C36: =SUM(C30:C35) -> 6 | D36: =SUM(D30:D35) -> 2 | E36: =SUM(E30:E35) -> 2 | H36: =SUM(H30:H35) -> 8 | I36: =SUM(I30:I35) -> 25 | J36: =SUM(I36+H36) -> 33
B37: SEMANA 7
B38: Vendedor | C38: pica extremo | D38: pica rico | E38: pica suave | F38: Extremo pequeño | G38: Rico pequeño | H38: Combo | I38: Subtotal | J38: TOTAL
B39: Alexandra
B40: Gerson
B41: Keren
B42: Nicolle
B43: Sthepany
B44: Tomas
B45: TOTAL | C45: =SUM(C39:C44) -> 0 | D45: =SUM(D39:D44) -> 0 | E45: =SUM(E39:E44) -> 0 | H45: =SUM(H39:H44) -> 0 | I45: =SUM(I39:I44) -> 0 | J45: =SUM(I45+H45) -> 0
B46: SEMANA 8
B47: Vendedor | C47: pica extremo | D47: pica rico | E47: pica suave | H47: SUB UNIDADES | I47: COMBO | J47: TOTAL
B48: Alexandra
B49: Gerson
B50: Keren
B51: Nicolle
B52: Sthepany
B53: Tomas
B54: TOTAL | C54: =SUM(C48:C53) -> 0 | D54: =SUM(D48:D53) -> 0 | E54: =SUM(E48:E53) -> 0 | H54: =SUM(H48:H53) -> 0 | I54: =SUM(I48:I53) -> 0 | J54: =SUM(I54+H54) -> 0
B55: SEMANA 9
B56: Vendedor | C56: pica extremo | D56: pica rico | E56: pica suave | H56: SUB UNIDADES | I56: COMBO | J56: TOTAL
B57: Alexandra
B58: Gerson
B59: Keren
B60: Nicolle
B61: Sthepany
B62: Tomas
B63: TOTAL | C63: =SUM(C57:C62) -> 0 | D63: =SUM(D57:D62) -> 0 | E63: =SUM(E57:E62) -> 0 | H63: =SUM(H57:H62) -> 0 | I63: =SUM(I57:I62) -> 0 | J63: =SUM(I63+H63) -> 0
B64: SEMANA 10
B65: Vendedor | C65: pica extremo | D65: pica rico | E65: pica suave | H65: SUB UNIDADES | I65: COMBO | J65: TOTAL
B66: Alexandra
B67: Gerson
B68: Keren
B69: Nicolle
B70: Sthepany
B71: Tomas
B72: TOTAL | C72: =SUM(C66:C71) -> 0 | D72: =SUM(D66:D71) -> 0 | E72: =SUM(E66:E71) -> 0 | H72: =SUM(H66:H71) -> 0 | I72: =SUM(I66:I71) -> 0 | J72: =SUM(I72+H72) -> 0
B73: SEMANA 11
B74: Vendedor | C74: pica extremo | D74: pica rico | E74: pica suave | H74: SUB UNIDADES | I74: COMBO | J74: TOTAL
B75: Alexandra
B76: Gerson
B77: Keren
B78: Nicolle
B79: Sthepany
B80: Tomas
B81: TOTAL | C81: =SUM(C75:C80) -> 0 | D81: =SUM(D75:D80) -> 0 | E81: =SUM(E75:E80) -> 0 | H81: =SUM(H75:H80) -> 0 | I81: =SUM(I75:I80) -> 0 | J81: =SUM(I81+H81) -> 0
B82: SEMANA 12
B83: Vendedor | C83: pica extremo | D83: pica rico | E83: pica suave | H83: SUB UNIDADES | I83: COMBO | J83: TOTAL
B84: Alexandra
B85: Gerson
B86: Keren
B87: Nicolle
B88: Sthepany
B89: Tomas
B90: TOTAL | C90: =SUM(C84:C89) -> 0 | D90: =SUM(D84:D89) -> 0 | E90: =SUM(E84:E89) -> 0 | H90: =SUM(H84:H89) -> 0 | I90: =SUM(I84:I89) -> 0 | J90: =SUM(I90+H90) -> 0

Sheet Base de datos clientes
A1: ID | B1: Nombre | C1: Telefono | D1: Profesion | E1: Empresa | F1: Ciudad | G1: Compras | H1: Estado
A2: CLI-001 | B2: Abraham Figueroa | C2: 94072826 | D2: Docente | E2: UNAH | F2: Tegucigalpa | H2: Activo
A3: CLI-002 | B3: Activacion Televicentro | C3: 92263088 | D3: Estudiante | E3: Independiente | F3: Tegucigalpa | H3: Activo
A4: CLI-003 | B4: Alex Maradiaga | C4: 8959-4167 | D4: Licenciado | E4: Grupo Flores | F4: Tegucigalpa | H4: Activo
A5: CLI-004 | B5: Allan Cruz | C5: 9693-0988 | D5: Docente | E5: Grupo Flores | F5: Tegucigalpa | H5: Activo
A6: CLI-005 | B6: Ana Suazo | C6: 8959-4169 | D6: Licenciado | E6: Empresa Privada | F6: Tegucigalpa | H6: Activo
A7: CLI-006 | B7: Anny Nicolle | C7: 9470 6313 | D7: Ingeniero | E7: UNAH | F7: Tegucigalpa | H7: Activo
A8: CLI-007 | B8: Bayron Robles | C8: 3340-7611 | D8: Ingeniero | E8: Empresa Privada | F8: Tegucigalpa | H8: Activo
A9: CLI-008 | B9: Brian Edgardo funes | C9: 88916581 | D9: Vendedor | E9: Claro | F9: Tegucigalpa | H9: Activo
A10: CLI-009 | B10: Bryan Christian Cruz | C10: 94428006 | D10: Licenciado | E10: UNAH | F10: Tegucigalpa | H10: Activo
A11: CLI-010 | B11: Bryan Oneal | C11: 9849-5689 | D11: Estudiante | E11: Independiente | F11: Tegucigalpa | H11: Activo
A12: CLI-011 | B12: Camila Rosales | C12: 9668-7434 | D12: Administrador | E12: Indufesa | F12: Tegucigalpa | H12: Activo
A13: CLI-012 | B13: Carlos Fernando | C13: 8852-9078 | D13: Licenciado | E13: Independiente | F13: Tegucigalpa | H13: Activo
A14: CLI-013 | B14: Carlos Josiel Hernandez | C14: 99334283 | D14: Licenciado | E14: UNAH | F14: Tegucigalpa | G14: 4 | H14: Activo
A15: CLI-014 | B15: Cesar Cruz | C15: 99909477 | D15: Licenciado | E15: Indufesa | F15: Tegucigalpa | H15: Activo
A16: CLI-015 | B16: Cristhian Israel | C16: 8794-6911 | D16: Contador | E16: Televicentro | F16: Tegucigalpa | H16: Activo
A17: CLI-016 | B17: Cristian Padilla | C17: 9203-9396 | D17: Licenciado | E17: UNAH | F17: Tegucigalpa | H17: Activo
A18: CLI-017 | B18: Daniel Isaac | C18: 89723363 | D18: Contador | E18: Indufesa | F18: Tegucigalpa | H18: Activo
A19: CLI-018 | B19: Daphne Naomi Ordoñez Martinez | C19: 9693-0986 | D19: Estudiante | E19: Empresa Privada | F19: Tegucigalpa | H19: Activo
A20: CLI-019 | B20: David Castillo | C20: 98805732 | D20: Licenciado | E20: UNAH | F20: Tegucigalpa | H20: Activo
A21: CLI-020 | B21: David Josue Gomez Nuñez | C21: 9469 6313 | D21: Estudiante | E21: Televicentro | F21: Tegucigalpa | H21: Activo
A22: CLI-021 | B22: Diana Flores | C22: 99909481 | D22: Estudiante | E22: Grupo Flores | F22: Tegucigalpa | H22: Activo
A23: CLI-022 | B23: Dilcia UNAH | C23: 9468 6313 | D23: Licenciado | E23: UNAH | F23: Tegucigalpa | H23: Activo
A24: CLI-023 | B24: Dionicio Indufesa | C24: 3292-7698 | D24: Docente | E24: Grupo Flores | F24: Tegucigalpa | H24: Activo
A25: CLI-024 | B25: Emely G. negocios | C25: 9668-7436 | D25: Vendedor | E25: Indufesa | F25: Tegucigalpa | H25: Activo
A26: CLI-025 | B26: Erika Dayana | C26: 8794-6910 | D26: Estudiante | E26: Estudiante | F26: Tegucigalpa | H26: Activo
A27: CLI-026 | B27: Estefany Meza | C27: 94652225 | D27: Administrador | E27: Empresa Privada | F27: Tegucigalpa | H27: Activo
A28: CLI-027 | B28: Evelyn Andino | C28: 3292-7695 | D28: Indepediente | F28: Tegucigalpa | H28: Activo
A29: CLI-028 | B29: Exon Sierra | C29: 8794-6912 | D29: Administrador | E29: Televicentro | F29: Tegucigalpa | H29: Activo
A30: CLI-029 | B30: Fabiola Romero | C30: 96970002 | D30: Docente | E30: UNAH | F30: Tegucigalpa | H30: Activo
A31: CLI-030 | B31: Fabricio Alex | C31: 93518096 | D31: Ingeniero | E31: Estudiante | F31: Tegucigalpa | H31: Activo
A32: CLI-031 | B32: Fanys Moreno | C32: 33647571 | D32: Licenciado | E32: Empresa Privada | F32: Tegucigalpa | H32: Activo
A33: CLI-032 | B33: Fernando Duarte | C33: 89417578 | D33: Docente | E33: Estudiante | F33: Tegucigalpa | H33: Activo
A34: CLI-033 | B34: Francisco Abularach | C34: 94546478 | D34: Gerente de ventas | E34: Indufesa | F34: Tegucigalpa | H34: Activo
A35: CLI-034 | B35: Franklin Paredes | C35: 99909478 | D35: Estudiante | E35: Estudiante | F35: Tegucigalpa | H35: Activo
A36: CLI-035 | B36: Gerson Sevilla | C36: 3340-7612 | D36: Licenciado | E36: Indufesa | F36: Tegucigalpa | H36: Activo
A37: CLI-036 | B37: Gladis Esther Arguijo Matute | C37: 9668-7433 | D37: Docente | E37: UNAH | F37: Tegucigalpa | H37: Activo
A38: CLI-037 | B38: Gracia Maria | C38: 9203-9397 | D38: Estudiante | E38: Independiente | F38: Tegucigalpa | H38: Activo
A39: CLI-038 | B39: Helen Perez | C39: 32487353 | D39: Contador | E39: Empresa Privada | F39: Tegucigalpa | H39: Activo
A40: CLI-039 | B40: Hever Perdomo | C40: 33323464 | D40: Contador | E40: Televicentro | F40: Tegucigalpa | H40: Activo
A41: CLI-040 | B41: Ingris G. negocios | C41: 9467 6313 | D41: Administrador | E41: Grupo Flores | F41: Tegucigalpa | H41: Activo
A42: CLI-041 | B42: Jeremy Emanuel | C42: 9898 1307 | D42: Ingeniero | E42: Indufesa | F42: Tegucigalpa | H42: Activo
A43: CLI-042 | B43: Jose Matute | C43: 3340-7608 | D43: Ingeniero | E43: Indufesa | F43: Tegucigalpa | H43: Activo
A44: CLI-043 | B44: Jose Roberto | C44: 97174763 | D44: Licenciado | E44: Estudiante | F44: Tegucigalpa | H44: Activo
A45: CLI-044 | B45: Josue Gomez | C45: 9203-9395 | D45: Contador | E45: Televicentro | F45: Tegucigalpa | H45: Activo
A46: CLI-045 | B46: Julio Hernandez | C46: 9849-5688 | D46: Estudiante | E46: Grupo Flores | F46: Tegucigalpa | H46: Activo
A47: CLI-046 | B47: Karen Fabiola | C47: 9693-0984 | D47: Licenciado | E47: Independiente | F47: Tegucigalpa | H47: Activo
A48: CLI-047 | B48: Karen Suyapa Lopez | C48: 94805781 | D48: Estudiante | E48: Empresa Privada | F48: Tegucigalpa | H48: Activo
A49: CLI-048 | B49: Keily Vargas | C49: 95501700 | D49: Docente | E49: UNAH | F49: Tegucigalpa | G49: 5 | H49: Activo
A50: CLI-049 | B50: Kelvin Daniel | C50: 99909480 | D50: Estudiante | E50: Grupo Flores | F50: Tegucigalpa | H50: Activo
A51: CLI-050 | B51: Karim Josue Matute | C51: 89554693 | D51: Emprendedor | E51: Independiente | F51: Tegucigalpa | H51: Activo
A52: CLI-051 | B52: Lamber Giron | C52: 94706222 | D52: Docente | E52: Grupo Flores | F52: Tegucigalpa | H52: Activo
A53: CLI-052 | B53: Leonor Jaqueline | C53: 9668-7432 | D53: Docente | E53: UNAH | F53: Tegucigalpa | H53: Activo
A54: CLI-053 | B54: Lucia Herrera | C54: 8852-9074 | D54: Licenciado | E54: Empresa Privada | F54: Tegucigalpa | H54: Activo
A55: CLI-054 | B55: Maria Steffa | C55: 9887-2330 | D55: Docente | E55: Grupo Flores | F55: Tegucigalpa | H55: Activo
A56: CLI-055 | B56: Marvin Antonio Medina Avila | C56: 8959-4165 | D56: Licenciado | E56: Televicentro | F56: Tegucigalpa | H56: Activo
A57: CLI-056 | B57: Marvin Castro | C57: 3292-7694 | D57: Estudiante | E57: Indufesa | F57: Tegucigalpa | H57: Activo
A58: CLI-057 | B58: Melissa Canaca | C58: 9668-7435 | D58: Ingeniero | E58: Televicentro | F58: Tegucigalpa | H58: Activo
A59: CLI-058 | B59: Melissa Fernandez | C59: 9849-5691 | D59: Licenciado | E59: Grupo Flores | F59: Tegucigalpa | H59: Activo
A60: CLI-059 | B60: Melvin Indufesa | C60: 9203-9399 | D60: Ingeniero | E60: Televicentro | F60: Tegucigalpa | H60: Activo
A61: CLI-060 | B61: Miguel Romero | C61: 3340-7609 | D61: Estudiante | E61: Estudiante | F61: Tegucigalpa | H61: Activo
A62: CLI-061 | B62: Monica Lagos | C62: 9693-0987 | D62: Administrador | E62: Grupo Flores | F62: Tegucigalpa | H62: Activo
A63: CLI-062 | B63: Nancy Daniela | C63: 8852-9076 | D63: Licenciado | E63: Empresa Privada | F63: Tegucigalpa | H63: Activo
A64: CLI-063 | B64: Nelson Cabrera | C64: 8794-6909 | D64: Estudiante | E64: Televicentro | F64: Tegucigalpa | H64: Activo
... A73: CLI-072 | B73: Sharon Raudales | C73: 8794-6913 | D73: Licenciado | E73: UNAH | F73: Tegucigalpa | H73: Activo
A74: CLI-073 | B74: Stefany Guillen Caex | C74: 99909479 | D74: Contador | E74: Indufesa | F74: Tegucigalpa | H74: Activo
A75: CLI-074 | B75: Stephani Daniela | C75: 8959-4168 | D75: Ingeniero | E75: Independiente | F75: Tegucigalpa | H75: Activo
A76: CLI-075 | B76: Suyapa Gisell | C76: 8959-4166 | D76: Licenciado | E76: Indufesa | F76: Tegucigalpa | H76: Activo
A77: CLI-076 | B77: Thayli Jihre | C77: 99315120 | D77: Estudiante | E77: Independiente | F77: San pedro Sula | H77: Activo
A78: CLI-077 | B78: Yolin Yamilet | C78: 8852-9077 | D78: Estudiante | E78: Independiente | F78: Tegucigalpa | H78: Activo
A79: CLI-078 | B79: Jefri Johan Galo | C79: 9203-9398 | D79: Estudiante | E79: Independiente | F79: Tegucigalpa | H79: Activo

Sheet Plan de ventas
A1: PLAN DE VENTAS PIKAZO
A2: SEMANA 1 | D2: SEMANA 2
A3: Actividad | B3: Estrategias de venta | C3: Meta de venta | D3: Actividad | E3: Estrategias de venta | F3: Meta de venta
A4: Lanzamiento del producto | B4: Realizar degustaciones de carne acompañada con salsa PIKA-ZO. | C4: Alcanzar una meta de 60 unidades vendidas durante la semana. | D4: Posicionamiento comercial | E4: 1. Cada integrante del grupo andar muestras de botes pequeños de las 3 intensidades para poder dar a degustar a los prospecto clientes | F4: 8 chiles picantes por vendedor
B5: Explicar las características, beneficios y presentación del producto. | E5: 2. Promocion de un 10% al repostear un post de nuestras redes sociales | F5: Meta total de la semana de 48 chiles picantes
B6: Incentivar a los asistentes a seguir las redes sociales de la marca. | E6: 3.Gestionar la participación en Canal 5 para promocionar el producto.
B7: Registrar posibles clientes interesados.
